JavaXunijiDicengYuanliZhishiZongjieFix1/README.md
JavaXunijiDicengYuanliZhishiZongjieFix1/__init__.py
JavaXunijiDicengYuanliZhishiZongjieFix1/__main__.py
JavaXunijiDicengYuanliZhishiZongjieFix1/file.epub
JavaXunijiDicengYuanliZhishiZongjieFix1/index.html
JavaXunijiDicengYuanliZhishiZongjieFix1/css/__init__.py
JavaXunijiDicengYuanliZhishiZongjieFix1/css/annotations.css
JavaXunijiDicengYuanliZhishiZongjieFix1/css/main.css
JavaXunijiDicengYuanliZhishiZongjieFix1/css/normalize.css
JavaXunijiDicengYuanliZhishiZongjieFix1/css/popup.css
JavaXunijiDicengYuanliZhishiZongjieFix1/font/__init__.py
JavaXunijiDicengYuanliZhishiZongjieFix1/font/fontello.eot
JavaXunijiDicengYuanliZhishiZongjieFix1/font/fontello.svg
JavaXunijiDicengYuanliZhishiZongjieFix1/font/fontello.ttf
JavaXunijiDicengYuanliZhishiZongjieFix1/font/fontello.woff
JavaXunijiDicengYuanliZhishiZongjieFix1/img/__init__.py
JavaXunijiDicengYuanliZhishiZongjieFix1/img/annotator-glyph-sprite.png
JavaXunijiDicengYuanliZhishiZongjieFix1/img/annotator-icon-sprite.png
JavaXunijiDicengYuanliZhishiZongjieFix1/img/apple-touch-icon.png
JavaXunijiDicengYuanliZhishiZongjieFix1/img/cancelfullscreen.png
JavaXunijiDicengYuanliZhishiZongjieFix1/img/close.png
JavaXunijiDicengYuanliZhishiZongjieFix1/img/fullscreen.png
JavaXunijiDicengYuanliZhishiZongjieFix1/img/loader.gif
JavaXunijiDicengYuanliZhishiZongjieFix1/img/menu-icon.png
JavaXunijiDicengYuanliZhishiZongjieFix1/img/save.png
JavaXunijiDicengYuanliZhishiZongjieFix1/img/saved.png
JavaXunijiDicengYuanliZhishiZongjieFix1/img/settings-s.png
JavaXunijiDicengYuanliZhishiZongjieFix1/img/settings.png
JavaXunijiDicengYuanliZhishiZongjieFix1/img/star.png
JavaXunijiDicengYuanliZhishiZongjieFix1/js/__init__.py
JavaXunijiDicengYuanliZhishiZongjieFix1/js/epub.js
JavaXunijiDicengYuanliZhishiZongjieFix1/js/epub.min.js
JavaXunijiDicengYuanliZhishiZongjieFix1/js/epub.min.map
JavaXunijiDicengYuanliZhishiZongjieFix1/js/hooks.min.js
JavaXunijiDicengYuanliZhishiZongjieFix1/js/hooks.min.map
java_xuniji_diceng_yuanli_zhishi_zongjie_fix1-2025.3.25.0.dist-info/METADATA
java_xuniji_diceng_yuanli_zhishi_zongjie_fix1-2025.3.25.0.dist-info/WHEEL
java_xuniji_diceng_yuanli_zhishi_zongjie_fix1-2025.3.25.0.dist-info/entry_points.txt
java_xuniji_diceng_yuanli_zhishi_zongjie_fix1-2025.3.25.0.dist-info/top_level.txt
java_xuniji_diceng_yuanli_zhishi_zongjie_fix1-2025.3.25.0.dist-info/RECORD
